{
   "name": "Navacer",
   "description": "T4 unit. Have shield, can shoot",
   "health": 1020,
   "armor": 17,
   "speed": 3.2,
   "flying": true,
   "TargetAir": true,
   "bulidSpeed": 3.5,
   "range": 280,
   "hitSize": 30,
   "rotateSpeed": 1.5,
   "weapons": [
    {
     "name": "dai_otdohnut_inogda",
     "reload": 60,
     "recoil": 18,
     "bullet": {
      "damage": 250,
      "speed": 2.3,
      "width": 50,
      "height": 50,
      "type": "BasicBulletType"
     }
    },
    {
     "name": "pupsgun",
     "reload": 30,
     "recoil": 10,
     "bullet": {
      "damage": 50,
      "width": 18,
      "speed": 3.6,
      "height": 18,
      "type": "BasicBulletType"
     }
    }
   ],
   "abilities": [
    {
     "type": "ForceFieldAbility",
     "regen": 2.8,
     "radius": 70,
     "max": 1020,
     "sides": 10
    }
   ]
}